djangocms_fomantic_ui/README.md
djangocms_fomantic_ui/__about__.py
djangocms_fomantic_ui/__init__.py
djangocms_fomantic_ui/admin.py
djangocms_fomantic_ui/apps.py
djangocms_fomantic_ui/cms_plugins.py
djangocms_fomantic_ui/models.py
djangocms_fomantic_ui/tests.py
djangocms_fomantic_ui/views.py
djangocms_fomantic_ui/locale/de/LC_MESSAGES/django.mo
djangocms_fomantic_ui/locale/de/LC_MESSAGES/django.po
djangocms_fomantic_ui/migrations/0001_initial.py
djangocms_fomantic_ui/migrations/0001_squashed_0052_delete_event.py
djangocms_fomantic_ui/migrations/0053_alter_accordionsection_title_and_more.py
djangocms_fomantic_ui/migrations/__init__.py
djangocms_fomantic_ui/static/phi_plugins/images/Stellaris_Clapper-board.svg
djangocms_fomantic_ui/templates/djangocms_fomantic_ui/accordion.html
djangocms_fomantic_ui/templates/djangocms_fomantic_ui/accordion_section.html
djangocms_fomantic_ui/templates/djangocms_fomantic_ui/button.html
djangocms_fomantic_ui/templates/djangocms_fomantic_ui/buttons.html
djangocms_fomantic_ui/templates/djangocms_fomantic_ui/card.html
djangocms_fomantic_ui/templates/djangocms_fomantic_ui/cards.html
djangocms_fomantic_ui/templates/djangocms_fomantic_ui/column.html
djangocms_fomantic_ui/templates/djangocms_fomantic_ui/div.html
djangocms_fomantic_ui/templates/djangocms_fomantic_ui/div_container.html
djangocms_fomantic_ui/templates/djangocms_fomantic_ui/embed.html
djangocms_fomantic_ui/templates/djangocms_fomantic_ui/generic_plugin.html
djangocms_fomantic_ui/templates/djangocms_fomantic_ui/icon.html
djangocms_fomantic_ui/templates/djangocms_fomantic_ui/message.html
djangocms_fomantic_ui/templates/djangocms_fomantic_ui/modal.html
djangocms_fomantic_ui/templates/djangocms_fomantic_ui/reveal.html
djangocms_fomantic_ui/templates/djangocms_fomantic_ui/row.html
djangocms_fomantic_ui/templates/djangocms_fomantic_ui/segment.html
djangocms_fomantic_ui/templates/djangocms_fomantic_ui/site_icons.html
djangocms_fomantic_ui/templates/djangocms_fomantic_ui/staff.html
djangocms_fomantic_ui-0.0.1.dist-info/METADATA
djangocms_fomantic_ui-0.0.1.dist-info/WHEEL
djangocms_fomantic_ui-0.0.1.dist-info/licenses/LICENSE.txt
djangocms_fomantic_ui-0.0.1.dist-info/RECORD
