Metadata-Version: 2.1
Name: djangocms-fomantic-ui
Version: 0.0.1
Project-URL: Documentation, https://github.com/MacLake/djangocms-fomantic-ui#readme
Project-URL: Issues, https://github.com/MacLake/djangocms-fomantic-ui/issues
Project-URL: Source, https://github.com/MacLake/djangocms-fomantic-ui
Author-email: Jens-Erik Weber <Jens-Erik.Weber@passiv.de>
License-Expression: MIT
License-File: LICENSE.txt
Classifier: Development Status :: 4 - Beta
Classifier: Programming Language :: Python
Classifier: Programming Language :: Python :: 3.9
Classifier: Programming Language :: Python :: 3.10
Classifier: Programming Language :: Python :: 3.11
Classifier: Programming Language :: Python :: Implementation :: CPython
Classifier: Programming Language :: Python :: Implementation :: PyPy
Requires-Python: >=3.9
